MANIFEST.in
README.md
setup.py
blt/__init__.py
blt/environment.py
blt/helpers.py
blt/main.py
blt.egg-info/PKG-INFO
blt.egg-info/SOURCES.txt
blt.egg-info/dependency_links.txt
blt.egg-info/entry_points.txt
blt.egg-info/requires.txt
blt.egg-info/top_level.txt
blt/test/__init__.py
blt/test/beltenvtest.py
blt/test/importedtest.py
blt/test/test_aws.py
blt/test/test_bundle.py
blt/test/test_django.py
blt/test/test_environment.py
blt/test/test_heroku.py
blt/test/test_south.py
blt/tools/__init__.py
blt/tools/aws.py
blt/tools/bundle.py
blt/tools/django.py
blt/tools/heroku.py
blt/tools/south.py