Metadata-Version: 1.1
Name: blt
Version: 0.2.0
Summary: blt - provides simple CLI superpowers.
Home-page: https://github.com/dencold/blt/
Author: Dennis Coldwell
Author-email: dennis.coldwell@gmail.com
License: BSD
Platform: UNKNOWN
Classifier: Development Status :: 4 - Beta
Classifier: Intended Audience :: Developers
Classifier: Natural Language :: English
Classifier: License :: OSI Approved :: BSD License
Classifier: Programming Language :: Python
Classifier: Programming Language :: Python :: 2.7
